{
   "title": "Adult Education",
   "preceded-by": [
      {"id": "adulteducbul", "note": "Adult Education Bulletin"},
      {"id": "adulteducjnl", "note": "Adult Education Journal"}
   ],
   "first-issue": {"issue-date": "1950-10", "volume": "1", "number": "1"},
   "first-renewed-issue": "none",
   "first-renewed-issue-source": "cce+database",
   "first-renewed-contribution": "none",
   "first-renewed-contribution-source": "cce+database",
   "last-issue": {"issue-date": "1983-Winter", "volume": "33", "number": "2"},
   "succeeded-by":
      [{"id": "adulteducqtly", "note": "Adult Education Quarterly"}],
   "responsibility": {
      "authorized": "Mark Ockerbloom, John, 1966-",
      "contact": "ockerblo@pobox.upenn.edu"
   },
   "last-updated": "2020-09-21"
}
