{
   "title": "The Black Mask",
   "online": "1",
   "contents": [
      {"url": "http://www.philsp.com/homeville/CFI/link.asp?magid=BLMSK",
       "note": "FictionMags Index"}
   ],
   "first-issue": {"issue-date": "1920-04", "volume": "1", "number": "1"},
   "first-renewed-issue": 
           {"issue-date": "1924-02-01", "cdate": "1924-01-12",
            "volume": "6", "number": "21"},
   "first-renewed-issue-source": "1951-JulDec",
   "first-renewed-contribution": 
      {"issue": {"issue-date": "1927-09", "volume": "10", "number": "7"}},
   "first-renewed-contribution-source": "1955-JanJun",
   "renewed-issue-completeness": "active/1924",
   "renewed-issues": [
           {"issue-date": "1924-02-01", "volume": "6", "number": "21"},
           {"issue-date": "1924-02-15", "volume": "6", "number": "22"},
           {"issue-date": "1924-03-01", "volume": "6", "number": "23"},
           {"issue-date": "1924-03-15", "volume": "6", "number": "24"},
           {"issue-date": "1924-04-01", "volume": "7", "number": "1"},
           {"issue-date": "1924-04-15", "volume": "7", "number": "2"},
           {"issue-date": "1924-05", "volume": "7", "number": "3"},
           {"issue-date": "1924-06", "volume": "7", "number": "4"},
           {"issue-date": "1924-07", "volume": "7", "number": "5"},
           {"issue-date": "1924-08", "volume": "7", "number": "6"},
           {"issue-date": "1924-09", "volume": "7", "number": "7"},
           {"issue-date": "1924-10", "volume": "7", "number": "8"},
           {"issue-date": "1924-11", "volume": "7", "number": "9"},
           {"issue-date": "1924-12", "volume": "7", "number": "10"},
           {"issue-date": "1925-01", "volume": "7", "number": "11"},
           {"issue-date": "1925-02", "volume": "7", "number": "12"},
           {"issue-date": "1925-03", "volume": "8", "number": "1"},
           {"issue-date": "1925-04", "volume": "8", "number": "2"},
           {"issue-date": "1925-05", "volume": "8", "number": "3"},
           {"issue-date": "1925-06", "volume": "8", "number": "4"},
           {"issue-date": "1925-07", "volume": "8", "number": "5"},
           {"issue-date": "1925-08", "volume": "8", "number": "6"},
           {"issue-date": "1925-09", "volume": "8", "number": "7"},
           {"issue-date": "1925-10", "volume": "8", "number": "8"},
           {"issue-date": "1925-11", "volume": "8", "number": "9"}
   ],
   "responsibility": {
      "authorized": "Mark Ockerbloom, John, 1966-",
      "contact": "ockerblo@pobox.upenn.edu"
   },
   "last-updated": "2019-03-01"
}
