{
   "title": "Bulletin of the American Association of Petroleum Geologists",
   "aka": ["American Association of Petroleum Geologists Bulletin"],
   "online": "1",
   "contents": [
      {"url": "http://archives.datapages.com/data/browse/aapg-bulletin/",
      "note": "Publisher site (full text also available for subscription or payment)"}
   ],
   "first-renewed-issue":
     {"issue-date": "1927-01", "volume": "11", "number": "1"},
   "first-renewed-issue-source": "1955-JanJun",
   "first-renewed-contribution": "none",
   "first-renewed-contribution-source": "cce+database",
   "renewed-issue-completeness": "active/1928",
   "renewed-issues": [
     {"issue-date": "1927-01", "volume": "11", "number": "1"},
     {"issue-date": "1927-02", "volume": "11", "number": "2"},
     {"issue-date": "1927-03", "volume": "11", "number": "3"},
     {"issue-date": "1927-04", "volume": "11", "number": "4"},
     {"issue-date": "1927-05", "volume": "11", "number": "5"},
     {"issue-date": "1927-06", "volume": "11", "number": "6"},
     {"issue-date": "1927-07", "volume": "11", "number": "7"},
     {"issue-date": "1927-08", "volume": "11", "number": "8"},
     {"issue-date": "1927-09", "volume": "11", "number": "9"},
     {"issue-date": "1927-10", "volume": "11", "number": "10"},
     {"issue-date": "1927-11", "volume": "11", "number": "11"},
     {"issue-date": "1927-12", "volume": "11", "number": "12"},
     {"issue-date": "1928-01", "volume": "12", "number": "1"},
     {"issue-date": "1928-02", "volume": "12", "number": "2"},
     {"issue-date": "1928-03", "volume": "12", "number": "3"},
     {"issue-date": "1928-04", "volume": "12", "number": "4"},
     {"issue-date": "1928-05", "volume": "12", "number": "5"},
     {"issue-date": "1928-06", "volume": "12", "number": "6"},
     {"issue-date": "1928-07", "volume": "12", "number": "7"},
     {"issue-date": "1928-08", "volume": "12", "number": "8"},
     {"issue-date": "1928-09", "volume": "12", "number": "9"},
     {"issue-date": "1928-10", "volume": "12", "number": "10"},
     {"issue-date": "1927-11", "volume": "12", "number": "11"},
     {"issue-date": "1928-12", "volume": "12", "number": "12"},
     {"issue-date": "1929-01", "volume": "13", "number": "1"},
     {"issue-date": "1929-02", "volume": "13", "number": "2"},
     {"issue-date": "1929-03", "volume": "13", "number": "3"},
     {"issue-date": "1929-04", "volume": "13", "number": "4"},
     {"issue-date": "1929-05", "volume": "13", "number": "5"},
     {"issue-date": "1929-06", "volume": "13", "number": "6"},
     {"issue-date": "1929-07", "volume": "13", "number": "7"},
     {"issue-date": "1929-08", "volume": "13", "number": "8"},
     {"issue-date": "1929-09", "volume": "13", "number": "9"},
     {"issue-date": "1929-10", "volume": "13", "number": "10"},
     {"issue-date": "1929-11", "volume": "13", "number": "11"},
     {"issue-date": "1929-12", "volume": "13", "number": "12"}
   ],
   "responsibility": {
      "authorized": "Mark Ockerbloom, John, 1966-",
      "contact": "ockerblo@pobox.upenn.edu"
   },
   "last-updated": "2022-09-05"
}
