{
   "title": "Bulletin Philologique et Historique du Comité des Travaux Historiques et Scientifiques",
   "title-note": "1885-1912",
   "rights-statement": "NoC-US",
   "online": "1",
   "succeeded-by":
     [{"id": "bulphilhis1715",
       "note": "Bulletin Philologique et Historique (Jusqu'à 1715) du Comité des Travaux Historiques et Scientifiques"}],
   "responsibility": {
      "authorized": "Mark Ockerbloom, John, 1966-",
      "contact": "ockerblo@pobox.upenn.edu"
   },
   "acknowledgement": 
      "Thanks to Pete Sullivan for copyright research on this title.",
   "last-updated": "2024-03-18"
}
