{
   "title": "Canadian Journal of Agricultural Science",
   "preceded-by": [{"id": "scientificagri", "note": "Scientific Agriculture"}],
   "first-issue": {"issue-date": "1953-January-February", "volume": "33"},
   "first-renewed-issue": "none",
   "first-renewed-issue-source": "database",
   "first-renewed-contribution": "none",
   "first-renewed-contribution-source": "database",
   "last-issue": {"issue-date": "1956-November-December", "volume": "36"},
   "succeeded-by": [
     {"id": "cdnjanimalsci", "note": "Canadian Journal of Animal Science"},
     {"id": "cdnjplantsci", "note": "Canadian Journal of Plant Science"},
     {"id": "cdnjsoilsci", "note": "Canadian Journal of Soil Science"}
   ],
   "additional-note": "This is a Canadian publication. Its contents may still be copyrighted even without renewals or copyright notices, if they meet GATT copyright restoration requirements for works first published outside the US.",
   "responsibility": {
      "authorized": "Mark Ockerbloom, John, 1966-",
      "contact": "ockerblo@pobox.upenn.edu"
   },
   "last-updated": "2020-09-09"
}
