{
   "title": "Clarksville Chronicle",
   "aka": ["Clarksville Daily Chronicle",
           "Clarksville Evening Chronicle",
           "Clarksville Weekly Chronicle",
           "Weekly Clarksville Chronicle"],
   "online": "1",
   "rights-statement": "NoC-US",
   "last-issue": {"issue-date": "1890-03-05"},
   "succeeded-by":
     [{"id": "clarksvtnlfchr", "note": "Clarksville Leaf-Chronicle"}],
   "responsibility": {
      "authorized": "Mark Ockerbloom, John, 1966-",
      "contact": "ockerblo@pobox.upenn.edu"
   },
   "acknowledgement": 
      "Thanks to Scott F Andrews for copyright research on this title.",
   "last-updated": "2022-07-19"
}
