{
   "title": "The Columbus Dispatch",
   "title-note": "Mississippi newspaper",
   "aka": ["The Columbus Weekly Dispatch"],
   "online": "1",
   "rights-statement": "NoC-US",
   "see-also":
    [{"id": "columbohdisp", "note": "The Columbus Dispatch (Ohio newspaper)"}],
   "responsibility": {
      "authorized": "Mark Ockerbloom, John, 1966-",
      "contact": "ockerblo@pobox.upenn.edu"
   },
   "acknowledgement": 
      "Thanks to Scott F Andrews for copyright research on this title.",
   "last-updated": "2022-11-08"
}
