{
   "title": "Don Quichotte",
   "title-note": "Cairo, 1939-1940",
   "first-renewed-issue": "none",
   "first-renewed-issue-source": "cce",
   "first-renewed-contribution": "none",
   "first-renewed-contribution-source": "cce",
   "additional-note": 
      "This is an Egyptian publication. Its contents may still be copyrighted even without renewals or copyright notices, if they meet GATT copyright restoration requirements for works first published outside the US.",
   "responsibility": {
      "authorized": "Mark Ockerbloom, John, 1966-",
      "contact": "ockerblo@pobox.upenn.edu"
   },
   "last-updated": "2026-03-06"
}
