{
   "title": "Islandica",
   "online": "1",
   "first-renewed-issue": "none",
   "first-renewed-issue-source": "cce+database",
   "first-renewed-contribution": "none",
   "first-renewed-contribution-source": "cce+database",
   "additional-note": "There are no active renewals under the name 'Islandica', but monographs in the series might be renewed as books under their monograph titles.  We have not found any such renewals up to volume 20 (1930), but have not yet surveyed systematically past that date.",
   "responsibility": {
      "authorized": "Mark Ockerbloom, John, 1966-",
      "contact": "ockerblo@pobox.upenn.edu"
   },
   "last-updated": "2024-08-26"
}
