{
   "title": "The Journal of Business of the University of Chicago",
   "online": "1",
   "contents": [
      {"url": "https://www.jstor.org/journal/jbusiunivchic",
       "note": "JSTOR (full text also available for subscription or payment)"}
   ],
   "preceded-by": [{"id": "univjbusiness",
                    "note": "The University Journal of Business"}],
   "first-issue": 
     {"issue-date": "1928-01", "volume": "1", "number": "1"},
   "first-renewed-issue": 
     {"issue-date": "1941-04", "volume": "14", "number": "no. 2 part 1"},
   "first-renewed-issue-source": "1969",
   "first-renewed-contribution": "none",
   "first-renewed-contribution-source": "cce+database",
   "last-issue": {"issue-date": "1953-10", "volume": "26", "number": "4"},
   "succeeded-by": [{"id": "jbusiness1954", "note": "The Journal of Business"}],
   "additional-note": "The October 1953 issue was the last to use 'The Journal of Business of the University of Chicago' on the cover, but that title was still used in some inner pages of 1954 issues. Some early 1950s issues of this journal were renewed under the title 'Journal of Business'.",
   "responsibility": {
      "authorized": "Mark Ockerbloom, John, 1966-",
      "contact": "ockerblo@pobox.upenn.edu"
   },
   "acknowledgement": 
      "Thanks to Felice Gollotti for copyright research on this title.",
   "last-updated": "2024-02-23"
}
