{
   "title": "The Journeyman Barber",
   "online": "1",
   "aka": ["The Journeyman Barber, Hairdresser and Cosmetologist", 
           "The Journeyman Barber, Hairdresser, Cosmetologist and Proprietor",
           "Journeyman Barber and Beauty Culture"],
   "first-issue": {"issue-date": "1905-02", "volume": "1", "number": "1"},
   "first-renewed-issue": "none",
   "first-renewed-issue-source": "cce+database",
   "first-renewed-contribution": 
     {"issue": {"issue-date": "1938-04"}},
   "first-renewed-contribution-source": "1965-JanJun",
   "additional-notes": [
   "The only active contribution renewals for this periodical are listed in the Artwork section of the Catalog of Copyright Entries, and not in the Contributions to Periodicals section.",
   "This magazine's first actively renewed contribution is in an issue titled 'The Journeyman Barber, Hairdresser and Cosmetologist'. See the Online Books Page listings for more on this serial's title history."
   ],
   "responsibility": {
      "authorized": "Mark Ockerbloom, John, 1966-",
      "contact": "ockerblo@pobox.upenn.edu"
   },
   "last-updated": "2018-08-23"
}
