{
   "title": "Live Girl Stories",
   "contents": [
      {"url": "http://www.philsp.com/homeville/FMI/link.asp?magid=LIVEG",
      "note": "FictionMags"}
   ],
   "first-issue":
     {"issue-date": "1928-11", "volume": "1", "number": "1"},
   "first-renewed-issue": 
     {"issue-date": "1928-11", "volume": "1", "number": "1"},
   "first-renewed-issue-source": "1955-JulDec",
   "first-renewed-contribution": "none",
   "first-renewed-contribution-source": "cce",
   "last-issue":
     {"issue-date": "1929-04", "volume": "1", "number": "6"},
   "succeeded-by": [{"id": "moderngirlstories", "note": "Modern Girl Stories"}],
   "renewed-issue-completeness": "active/end",
   "renewed-issues": [
     {"issue-date": "1928-11", "volume": "1", "number": "1"},
     {"issue-date": "1928-12", "volume": "1", "number": "2"},
     {"issue-date": "1929-01", "volume": "1", "number": "3"},
     {"issue-date": "1929-02", "volume": "1", "number": "4"},
     {"issue-date": "1929-03", "volume": "1", "number": "5"},
     {"issue-date": "1929-04", "volume": "1", "number": "6"}
   ],
   "responsibility": {
      "authorized": "Mark Ockerbloom, John, 1966-",
      "contact": "ockerblo@pobox.upenn.edu"
   },
   "last-updated": "2020-02-25"
}
