{
   "title": "Maclean's",
   "title-note": "Canadian magazine",
   "online": "1",
   "preceded-by": [{"id": "busyman", "note": "The Busy Man's Magazine"}],
   "first-issue": {"issue-date": "1911-03", "volume": "21", "number": "5"},
   "first-renewed-issue": "none",
   "first-renewed-issue-source": "cce+database",
   "first-renewed-contribution": {"issue": {"issue-date": "1937-03-01"}},
   "first-renewed-contribution-source": "1964-JanJun",
   "additional-note": 
      "This is a Canadian publication. Its contents may still be copyrighted even without renewals or copyright notices, if they meet GATT copyright restoration requirements for works first published outside the US. However, issues from the first one onward show US branch addresses for the publisher and registration with the US postal service.",
   "responsibility": {
      "authorized": "Mark Ockerbloom, John, 1966-",
      "contact": "ockerblo@pobox.upenn.edu"
   },
   "acknowledgement": 
      "Thanks to Shelton Henderson for copyright research on this title.",
   "last-updated": "2020-06-05"
}
