{
   "title": "Marie Claire",
   "online": "1",
   "first-renewed-issue": "none",
   "first-renewed-issue-source": "cce+database",
   "first-renewed-contribution": {"issue": {"cdate": "1955-08-01"}},
   "first-renewed-contribution-source": "database",
   "additional-note": 
      "This is a French publication. Its contents may still be copyrighted even without renewals or copyright notices, if they meet GATT copyright restoration requirements for works first published outside the US. A US-specific edition is currently published, but did not begin until the 1990s.",
   "responsibility": {
      "authorized": "Mark Ockerbloom, John, 1966-",
      "contact": "ockerblo@pobox.upenn.edu"
   },
   "acknowledgement": 
      "Thanks to Pete Sullivan for copyright research on this title.",
   "last-updated": "2024-05-23"
}
