{
   "title": "Parade",
   "title-note": "1941-",
   "first-issue": 
      {"issue-date": "1941-07-13", "volume": "1", "number": "1"},
   "first-renewed-issue": "none",
   "first-renewed-issue-source": "cce+database",
   "first-renewed-contribution":
      {"issue": {"issue-date": "1954-05-16"}},
   "first-renewed-contribution-source": "database",
   "see-also":
      [{"id": "parade1936", "note": "Parade (1930s American publication(s))"}],
   "additional-note": "This American magazine has usually been published as a supplement insert to Sunday newspapers.",
   "responsibility": {
      "authorized": "Mark Ockerbloom, John, 1966-",
      "contact": "ockerblo@pobox.upenn.edu"
   },
   "last-updated": "2022-09-30"
}
